{
    "description": "",
    "tags": [],
    "size": {
        "height": 512,
        "width": 512
    },
    "objects": [
        {
            "id": 14804207,
            "classId": 21385,
            "description": "",
            "geometryType": "rectangle",
            "labelerLogin": "vo@datasetninja.com",
            "createdAt": "2023-07-13T15:17:04.440Z",
            "updatedAt": "2023-07-13T15:17:04.440Z",
            "tags": [],
            "classTitle": "crop",
            "points": {
                "exterior": [
                    [
                        1,
                        144
                    ],
                    [
                        472,
                        445
                    ]
                ],
                "interior": []
            }
        },
        {
            "id": 14804206,
            "classId": 21385,
            "description": "",
            "geometryType": "rectangle",
            "labelerLogin": "vo@datasetninja.com",
            "createdAt": "2023-07-13T15:17:04.440Z",
            "updatedAt": "2023-07-13T15:17:04.440Z",
            "tags": [],
            "classTitle": "crop",
            "points": {
                "exterior": [
                    [
                        1,
                        5
                    ],
                    [
                        120,
                        124
                    ]
                ],
                "interior": []
            }
        },
        {
            "id": 14804205,
            "classId": 21385,
            "description": "",
            "geometryType": "rectangle",
            "labelerLogin": "vo@datasetninja.com",
            "createdAt": "2023-07-13T15:17:04.440Z",
            "updatedAt": "2023-07-13T15:17:04.440Z",
            "tags": [],
            "classTitle": "crop",
            "points": {
                "exterior": [
                    [
                        302,
                        63
                    ],
                    [
                        404,
                        131
                    ]
                ],
                "interior": []
            }
        },
        {
            "id": 14804204,
            "classId": 21385,
            "description": "",
            "geometryType": "rectangle",
            "labelerLogin": "vo@datasetninja.com",
            "createdAt": "2023-07-13T15:17:04.440Z",
            "updatedAt": "2023-07-13T15:17:04.440Z",
            "tags": [],
            "classTitle": "crop",
            "points": {
                "exterior": [
                    [
                        1,
                        378
                    ],
                    [
                        173,
                        508
                    ]
                ],
                "interior": []
            }
        },
        {
            "id": 14804203,
            "classId": 21385,
            "description": "",
            "geometryType": "rectangle",
            "labelerLogin": "vo@datasetninja.com",
            "createdAt": "2023-07-13T15:17:04.440Z",
            "updatedAt": "2023-07-13T15:17:04.440Z",
            "tags": [],
            "classTitle": "crop",
            "points": {
                "exterior": [
                    [
                        127,
                        1
                    ],
                    [
                        231,
                        44
                    ]
                ],
                "interior": []
            }
        },
        {
            "id": 14804202,
            "classId": 21385,
            "description": "",
            "geometryType": "rectangle",
            "labelerLogin": "vo@datasetninja.com",
            "createdAt": "2023-07-13T15:17:04.440Z",
            "updatedAt": "2023-07-13T15:17:04.440Z",
            "tags": [],
            "classTitle": "crop",
            "points": {
                "exterior": [
                    [
                        405,
                        1
                    ],
                    [
                        511,
                        81
                    ]
                ],
                "interior": []
            }
        }
    ]
}