{
    "description": "",
    "tags": [],
    "size": {
        "height": 512,
        "width": 512
    },
    "objects": [
        {
            "id": 14804648,
            "classId": 21385,
            "description": "",
            "geometryType": "rectangle",
            "labelerLogin": "vo@datasetninja.com",
            "createdAt": "2023-07-13T15:24:31.619Z",
            "updatedAt": "2023-07-13T15:24:31.619Z",
            "tags": [],
            "classTitle": "crop",
            "points": {
                "exterior": [
                    [
                        5,
                        17
                    ],
                    [
                        511,
                        511
                    ]
                ],
                "interior": []
            }
        }
    ]
}